better_namespaces/__init__.py
better_namespaces/context_group.py
better_namespaces-1.1.1.dist-info/METADATA
better_namespaces-1.1.1.dist-info/WHEEL
better_namespaces-1.1.1.dist-info/top_level.txt
better_namespaces-1.1.1.dist-info/RECORD
